music_organizer/__init__.py
music_organizer/main.py
music_organizer/setup.py
music_organizer-0.1.1.dist-info/LICENSE.txt
music_organizer-0.1.1.dist-info/WHEEL
music_organizer-0.1.1.dist-info/METADATA
music_organizer-0.1.1.dist-info/RECORD
