Metadata-Version: 2.1
Name: music-organizer
Version: 0.1.1
Summary: Music files organizer
License: MIT
Author: JOramas
Author-email: javiale2000@gmail.com
Requires-Python: >=3.7,<4.0
Classifier: License :: OSI Approved :: MIT License
Classifier: Programming Language :: Python :: 3
Classifier: Programming Language :: Python :: 3.10
Classifier: Programming Language :: Python :: 3.7
Classifier: Programming Language :: Python :: 3.8
Classifier: Programming Language :: Python :: 3.9
Requires-Dist: audio-metadata (>=0.11.1,<0.12.0)
Requires-Dist: typer (>=0.4.0,<0.5.0)
